HISTORY.rst
MANIFEST.in
flask_mandrill.py
setup.py
Flask_Mandrill.egg-info/PKG-INFO
Flask_Mandrill.egg-info/SOURCES.txt
Flask_Mandrill.egg-info/dependency_links.txt
Flask_Mandrill.egg-info/not-zip-safe
Flask_Mandrill.egg-info/requires.txt
Flask_Mandrill.egg-info/top_level.txt