Metadata-Version: 1.0
Name: Flask-Mandrill
Version: 0.1.1
Summary: Adds Mandrill support to Flask applications
Home-page: http://github.com/volker48/flask-mandrill
Author: Marcus McCurdy
Author-email: marcus.mccurdy@gmail.com
License: MIT
Platform: any
Classifier: Development Status :: 4 - Beta
Classifier: Environment :: Web Environment
Classifier: Intended Audience :: Developers
Classifier: License :: OSI Approved :: MIT License
Classifier: Operating System :: OS Independent
Classifier: Programming Language :: Python
Classifier: Topic :: Internet :: WWW/HTTP :: Dynamic Content
Classifier: Topic :: Software Development :: Libraries :: Python Modules
